LICENSE
setup.py
yaoysTools/__init__.py
yaoysTools/data/__init__.py
yaoysTools/data/split_datautil.py
yaoysTools/data/split_files.py
yaoysTools/database/__init__.py
yaoysTools/database/mysql.py
yaoysTools/file/__init__.py
yaoysTools/file/file_util.py
yaoysTools/log/__init__.py
yaoysTools/log/logutil.py
yaoysTools/progress/__init__.py
yaoysTools/progress/bar.py
yaoysTools/progress/colors.py
yaoysTools/progress/counter.py
yaoysTools/progress/progressUtil.py
yaoysTools/progress/spinner.py
yaoysTools/text/__init__.py
yaoysTools/time/__init__.py
yaoysTools/time/timeutil.py
yaoysTools/toolsutil/__init__.py
yaoysTools/toolsutil/mathutil.py
yaoysTools/uniqueid/__init__.py
yaoysTools/uniqueid/snowflake.py
yaoys_python_tool.egg-info/PKG-INFO
yaoys_python_tool.egg-info/SOURCES.txt
yaoys_python_tool.egg-info/dependency_links.txt
yaoys_python_tool.egg-info/requires.txt
yaoys_python_tool.egg-info/top_level.txt