Metadata-Version: 2.1
Name: yaoys-python-tool
Version: 0.0.53
Summary: python工具类
Home-page: https://github.com/yaoysyao/PythonTools.git
Author: YaoYuanshuai
Author-email: yys9508@qq.com
License: UNKNOWN
Platform: UNKNOWN
Classifier: Programming Language :: Python :: 3
Classifier: License :: OSI Approved :: MIT License
Classifier: Operating System :: OS Independent
Requires-Python: >=3.7
License-File: LICENSE
